README.md
setup.py
pyrfloc/__init__.py
pyrfloc/rfloc.py
pyrfloc.egg-info/PKG-INFO
pyrfloc.egg-info/SOURCES.txt
pyrfloc.egg-info/dependency_links.txt
pyrfloc.egg-info/not-zip-safe
pyrfloc.egg-info/requires.txt
pyrfloc.egg-info/top_level.txt